{
  "id": 2903,
  "title": "آية الشيب",
  "slug": "آية-الشيب",
  "author": {
    "name_prefix": "الشيخ",
    "first_name": "أ.د عبدالله بن محمد",
    "last_name": "الطيار"
  },
  "rawContent": "عناصر الخطبة\n                        1/عظم آية الشيب 2/الشيب بداية مرحلة الضعف وقرب الأجل 3/فضل الشيب 4/حقوق أهل المشيب 5/ عظة للشباب وأهل الشيب\n                    \n                                                                                                                                                                                                                        \n                                \n                     اقتباس\n                    فبينما الإنسانُ يعيشُ أيامَ شبابِهِ في أوجِ قوّتهِ، وعنفوانِ فتوتِه، ويؤمَّل طولَ بقائهِ في الدنيا، وقد ملأَ أيّامها نشاطًا وحيويةً، وتعلّق قلبُه بطول العمر؛ إذ ينقلب كل ذلك؛ فورقات شجرةِ عمرهِ تتهافت، وسنواتُها تتعاقبْ، وأحوالُه تتغيَّر، ويذبلُ عزُّه، ويبدأ ذُله، فيبيضُّ شعرُه، ويتجعَّدُ وجهُه، ويحدودبُ ظهرُه، وتهنُ حواسُّه، وتضعفُ ذاكرتُه، وتتغيَّر عافيتُه؛ فالشيبُ هو ناقوسُ...\n                \n                                \n                \n                    الخطبة الأولى:\n \nإنّ الحمدَ للهِ نحمدهُ ونستعينهُ ونستغفرُه، ونعوذ بالله من شرور أنفسنا وسيئات أعمالنا، من يهده الله فلا مضل له، ومن يضلل فلا هادي له، وأشهدُ أن لا إله إلا اللهُ وحده لا شريك له، وأشهدُ أنّ محمدًا عبدُهُ ورسولُهُ صلى الله عليه وعلى آله وصحبه ومن تبعهم بإحسان إلى يوم الدين وسلّم تسليمًا كثيرًا.\n \nأمّا بعد: فاتقوا الله -عباد الله-، واعلموا أن التقوى طريقُ النجاة والفوز برضا الرحمن (يَا أَيُّهَا الَّذِينَ آمَنُوا اتَّقُوا اللَّهَ وَقُولُوا قَوْلاً سَدِيداً * يُصْلِحْ لَكُمْ أَعْمَالَكُمْ وَيَغْفِرْ لَكُمْ ذُنُوبَكُمْ وَمَن يُطِعِ اللهَ وَرَسُولَهُ فَقَدْ فَازَ فَوْزَاً عَظِيماً) [الأحزاب:70-71].\n \nعباد الله: لقد جعل اللهُ -تعالى- في خلقهِ آياتٍ عظيمةً، وبراهينَ عديدةً، تَظهرُ فيها قدرةُ وعظمةُ الخالق الجليل، وصدق الله -تعالى-: (سَنُرِيهِمْ آَيَاتِنَا فِي الْآَفَاقِ وَفِي أَنْفُسِهِمْ حَتَّى يَتَبَيَّنَ لَهُمْ أَنَّهُ الْحَقُّ)[فصلت: 53] وقال تعالى: (وَكَأَيِّنْ مِنْ آيَةٍ فِي السَّمَوَاتِ وَالأَرْضِ يَمُرُّونَ عَلَيْهَا وَهُمْ عَنْهَا مُعْرِضُونَ)[النحل: 105].\n \nومن تلك الآياتِ الباهرةِ التي غفل عنها كثيرٌ من الناسِ آيةُ المشيبِ التي تصيبُ الإنسانَ في آخرِ سنواتِ عمرهِ، تلك الآيةُ التي ذكرها اللهُ -تعالى- في كتابهِ العزيزِ كما في قوله -جلّ وعلا- عن زكريا عليه السلام: (قَالَ رَبِّ إِنِّي وَهَنَ الْعَظْمُ مِنِّي وَاشْتَعَلَ الرَّأْسُ شَيْباً وَلَمْ أَكُنْ بِدُعَائِكَ رَبِّ شَقِيّاً)[مريم:4].\n \nتلك الآيةُ العظيمةُ التي يُظهرِها اللهُ -تعالى- في كثيرٍ من خلقهِ ويغفلونَ عما وراءها من العبرِ والعظاتِ، والإنسانُ في هذهِ الدنيا يعيشُ بين ضَعْفَين، ضَعْفٌ في مبدأِ طفولتِهِ، ثم ضعفٍ وَوَهنٍ عند نهايتِهِ وشيخوختِه، وهذا الضعفُ والنقصُ المحاطُ به الإنسانُ، هو من جملةِ آياتِ اللهِ -تعالى- التي وضعها في خلقِهِ للاعتبارِ والتذكرِ؛ قال جلّ وعلا: (اللَّهُ الَّذِي خَلَقَكُمْ مِنْ ضَعْفٍ ثُمَّ جَعَلَ مِنْ بَعْدِ ضَعْفٍ قُوَّةً ثُمَّ جَعَلَ مِنْ بَعْدِ قُوَّةٍ ضَعْفًا وَشَيْبَةً يَخْلُقُ مَا يَشَاءُ وَهُوَ الْعَلِيمُ الْقَدِيرُ)[الروم:54]؛ فتعالوا بنا نقفُ مع ضعفٍ يسبقُنا، أو قد حلَّ ببعضِنا، مع الشيبِ والمشيبِ، وهمّهِ وهمومِه، وحلوهِ ومُرِّه، وعِبرِه وعَبَراتِهِ.\n \nأيّها المؤمنون والمؤمنات: حياةُ الكهولةِ والمشيبِ محطةٌ لا بدّ منها لمنْ أمدَّ اللهُ في عمرِهِ، وأنسأَ لهُ في أثرِهِ، وهي حياةٌ تبعثُ على الإشفاقِ، والرأفةِ، والرحمةِ.\n \nمرحلةٌ تحملُ في طيّاتها تغيرًا كثيرًا في الخلقةِ والطبعِ والطبائعِ.\n \nتأمّلوا معي -عباد الله- عظيمَ قدرةِ اللهِ وصُنعهِ في عبدِه؛ فبينما الإنسانُ يعيشُ أيامَ شبابِهِ في أوجِ قوّتهِ، وعنفوانِ فتوتِه، ويؤمَّل طولَ بقائهِ في الدنيا، وقد ملأَ أيّامها نشاطًا وحيويةً، وتعلّق قلبُه بطول العمر؛ إذ ينقلب كل ذلك؛ فورقات شجرةِ عمرهِ تتهافت، وسنواتُها تتعاقبْ، وأحوالُه تتغيَّر، ويذبلُ عزُّه، ويبدأ ذُله، فيبيضُّ شعرُه، ويتجعَّدُ وجهُه، ويحدودبُ ظهرُه، وتهنُ حواسُّه، وتضعفُ ذاكرتُه، وتتغيَّر عافيتُه؛ فالشيبُ هو ناقوسُ الضعفِ، ونذيرُ الفناءِ، والعجزِ بعد القوّةِ، والعلةُ التي لا تبرأُ، والدليلُ على قربِ الرحيلِ.\n \nوهو آيةٌ عظيمةٌ على قربِ نهايةِ عمر الإنسانِ، ومنتهى حياتِهِ، وصدقَ اللهُ -تعالى-: (وَمَنْ نُعَمِّرْهُ نُنَكِّسْهُ فِي الْخَلْقِ أَفَلا يَعْقِلُونَ)[يس: 68].\n \nوإذا شابَ المرءُ فقدْ أعذَرَه ربُّه بتعميرِه، وإمدادِهِ في فسحةِ حياتِهِ، وقد اشتدَّ عتابُ اللهِ على أقوامٍ عاشوا طويلاً، وامتدتْ حياتُهم، لكنّهم لم ينتفعوا بأعمارهمْ؛ قال تعالى: (أَوَلَمْ نُعَمِّرْكُمْ مَا يَتَذَكَّرُ فِيهِ مَنْ تَذَكَّرَ وَجَاءَكُمُ النَّذِيرُ فَذُوقُوا فَمَا لِلظَّالِمِينَ مِنْ نَصِيرٍ)[فاطر: 37]، وقد فسَّره بعضُ العلماءِ بأنّه الشيبُ.\n \nفأهلُ القلوبِ الحيَّةِ يعتبرون هذا الشيبَ نَذارةً من ربّهم؛ ليستعدوا بالعملِ، قبلَ حلولِ الأجلِ، فليسَ بعد هذا المشيبِ بضعفهِ ووهنهِ إلّا رذائلُ الأعمارِ، والانتقالُ من هذهِ الدّارِ.\n \nعبادَ اللهِ: إنّ هذا المشيبَ، وإنْ جاءَ بالضعفِ والعجزِ والحزنِ، إلا أنّه يحملُ بين طياتِهِ الأجرَ العظيمَ، والثوابَ الجزيلَ، لمن تحلّى بالصبرِ، وآمن بالقضاءِ والقدرِ؛ فهو في حياتِه كلّها في خيرٍ، وعلى خيرٍ، يقولُ -صلى الله عليه وسلم-: \"عجبًا لأمرِ المؤمنِ، إنّ أمرَهُ كلَّهُ خير، وليسَ ذاك لأحدٍ إلا للمؤمنِ، إن أصابتْهُ سرّاءُ شَكَرَ، فكانَ خيْرًا لهُ، وإنْ أصابتْهُ ضرّاءَ صبرَ، فكانَ خيْرًا لهُ\"(رواه مسلم).\n \nفأهلُ الشيبِ في الإسلامِ لهمْ من المكانةِ والفضلِ ما ليسَ لمنْ دونهمْ، فإنّ رسولَ اللهِ -صلى اللهُ عليه وسلّم- قَرَنَ إِجْلالَ اللهِ بإجلالِهِمْ ؛ قالَ -صلى الله عليه وسلم-: \"إنّ مِنْ إجلالِ اللهِ -تعالى- إكرامَ ذي الشيبةِ المسلمِ\"(رواه البخاري في الأدب المفرد، وأبو داود، وحسنه الألباني في سنن أبي داود).\n \nوكافأهم أيضًا بحطِّ السيّئاتِ، وزيادةِ الحسناتِ، ورفعةِ الدرجاتِ ؛ قال -صلى الله عليه وسلم-: \"لَا تَنْتِفُوا الشّيْبَ فَإِنّهُ مَا مِنْ مُسْلِمٍ يَشِيبُ شَيْبَةً فِي الإِسْلَامِ إلّا كتبَ اللهُ لهُ بِهَا حَسَنَةً وَحَطّ عنهُ بِهَا خَطِيئةً\"(رواه أبو داود والترمذي، وصححه الألباني في صحيح الترغيب والترهيب).\n \nوأبدلهـم -سبحانه وتعالى- بهذا الشيبِ نورًا؛ قال -صلى الله عليه وسلم-: \"مَنْ شَابَ شَيْبَةً فِي الِإسلامِ، كانتْ لهُ نورًا يومَ القِيَامةِ\"(رواه ابن حبان بسند حسن).\n \nوسُئل النبي -صلى الله عليه وسلم-: أيُّ النَّاسِ خيرٌ؟ قال: \"مَنْ طَالَ عُمْرُهُ وَحَسُنَ عَمَلُهُ\"، قال: فأيُّ النَّاسِ شرٌّ؟ قال: \"منْ طالَ عُمْرُهُ وَسَاءَ عَمَلُهُ\"(رواه الترمذي، وصححه الألباني في سنن الترمذي)؛ فطوبى لمنْ شابَ رأسُهُ، وابْيّضَ شعرُهُ، وهو مستقيمٌ على طاعة رَبّهِ. قال الحسنُ البصريُّ: \"أفضلُ الناسِ ثوابًا يومَ القيامةِ المؤمنُ المعمَّرُ\".\n \nفإذا استقامتْ أحوالُ أهلِ المشيبِ وصلَحتْ أعمالُهم وحسُنت سيرتُهم؛ كانوا أقربَ النّاسِ إلى ربّهم -عزّ وجلّ-، وأهلاً للرحمةِ وإجابةِ الدعاءِ.\n \nقال اللهُ -تعالى-: (اللَّهُ الَّذِي خَلَقَكُمْ مِنْ ضَعْفٍ ثُمَّ جَعَلَ مِنْ بَعْدِ ضَعْفٍ قُوَّةً ثُمَّ جَعَلَ مِنْ بَعْدِ قُوَّةٍ ضَعْفاً وَشَيْبَةً يَخْلُقُ مَا يَشَاءُ وَهُوَ الْعَلِيمُ الْقَدِيرُ)[الروم:54].\n \nباركَ اللهُ لي ولكُمْ في القرآنِ العظيمِ ونفعني وإياكمْ بما فيهِ من الآياتِ والذِّكْرِ الحكيمِ أقولُ قولي هذا وأستغفرُ اللهَ لي ولكمْ منْ كلِّ ذنْبٍ فاستغفروهُ؛ إنّهُ هو الغفورُ الرحيم.\n \n \nالخطبة الثانية:\n \nالحمدُ للهِ على فضلِهِ وإحسانِهِ، والشكرُ لهُ على توفيقِهِ وامتنانِهِ، وأشهدُ أنْ لا إلهَ إلّا اللهُ وحدهُ لا شريكَ لهُ، وأشهدُ أنّ محمدًا عبدُ اللهِ ورسولُهُ صلى اللهُ عليهِ وعلى آلهِ وصحبهِ ومنْ سارَ على نهجِهِ إلى يومِ الدّينِ.\n \nأمَا بعدُ:\n \nفيا أيها المؤمنون والمؤمنات: اتقوا الله –تعالى-، واعلموا أن تقواه سبيل إلى نيل رضاه وجنته.\n \nعباد الله: إنّ الشيبَ -وإنْ أَنِفَهُ بعضُ النّاس- يُعتبر عُنوانَ وَقارٍ وتَاجَ هيبةٍ ورمزَ إجلالٍ ورزانةٍ؛ فحرِيٌّ بمنْ ابيضّ عارضاهُ أنْ يحفظَ وقارَهُ وهيبتَه، وأن يبيّضَ صحيفتَهُ، وأنْ يكثرَ منْ حسناتِهِ.\n \nفعلينا أن نُوقِّر أهل المشيبِ ونَحترمُهُمْ، وأنْ نُصغِي لحديثِهِم، وأنْ نَقضي حَوائجهمْ، وأن نُقدّمهم في المجالسِ؛ لما روي عنْ أنس بن مالك -رضي الله عنه- قال: جاء شيخ غريب يريد النبيَّ -صلى الله عليه وسلم- فأبطأَ الناسُ أنْ يُوسِّعوا له، فقال النبي-صلى الله عليه وسلم-: \"ليسَ منّا مَنْ لمْ يرحمْ صغيرَنا، ويوقّر كبيرَنا\"(رواه الترمذي، وصححه الألباني في جامع الترمذي).\n \nولما روي أيضًا عن عبد الله بن عمر -رضي الله عنهما- أنّ رسول الله -صلى الله عليه وسلم- قال: \"إنَّ مِنَ الشّجَرِ شجرةً لا يسقطُ ورقُهَا وهو مثلُ المؤمنِ حدّثُوني ما هي؟\"، قال عبدُ الله: فوقعَ النّاسُ في شجرِ البوادي ووقعَ في نفسي أنّهَا النّخْلةُ، فقال النبي -صلى الله عليه وسلم-: \"هي النخلةُ\"، فاستحييت أنْ أقول. قال عبد الله: فحدّثت عمرَ بالذي وقعَ في نفسي، فقال: لأنْ تكونَ قلتَهَا أحبُّ إليَّ منْ أنْ يكونَ لي كذا وكذا\"(رواه الترمذي، وصححه الألباني في جامع الترمذي).\n \nوإنّي في مقامي هذا أخاطبُ شبابنَا ممنْ لم يروا المشيب، وأقول لهم: اعتبروا بغيرِكم، واتّعِظُوا بما ترونهُ أمامَ أعينِكُمْ، واعلموا أنّ زمنَ الصِّبا والفُتُوَّةِ ظِلٌّ زائل وبستانٌ ذابل، وتذكّروا أنّ زمنَ المشيبِ قريبٌ، وأنّ العمرَ يمضي والسنوَن تنقضي؛ فاملؤوا رصيدكم بالأعمالِ الصالحةِ، واستعينوا بقوّتكمْ على الإكثارِ من الحسناتِ، ولا تخدعنَّكم الدنيا بزخرفِها.\n \nوتذكَّرْ -يا من علاكَ الشيبُ- أن الفُسحةَ في العمرِ نعمةٌ كبيرةٌ يمنُّ الله بها على عبادهِ؛ فاستثمرْ هذه النّعمةَ فيما يُرضي ربَّكَ ويُعلِي منزلتَك، واستدرِك ما فاتَ بالاستعدادِ لما هو آتٍ. لتكنْ شعراتُ شيبكَ تؤزُّكَ للإِنابةِ إلى ربّك أزًّا، وتحرّك مشاعرَ النّدم في نفسِك على تقصيرك، وتضييعِ عمرِك فيما لا ينفعُ؛ فليس فيما بقي من العمر أطولُ مما فاتَ؛ فبادرْ بالتوبةِ والعمل بقيّة أيامك قبل أن تبادرك المنون، واجعل مسك ختام العمر طاعة وتقوى، صلاة وصيامًا، وصدقة واستغفارًا، سلِّ الله حُسن الخاتمة، واعلم أن من عاش على شيء مات عليه، وأن الأعمال بالخواتيم.\n \nأسأل الله -جل وعلا- أن يبارك لنا في شيوخنا وكبارنا، وأن يثبِّتنا وإياهم على الإيمان، وأن يزيدهم إحسانًا وتقى، وأن يُلبسهم لباسَ الصحة والعافية.\n \nوأسأله جل وعلا أن يجعل خير أعمارنا أواخرها، وخير أعمالنا خواتمهـا، وخير أيامنا يوم نلقاه؛ إنه سميع قريب مجيب.\n \nهذا وصلوا وسلموا على الحبيب المصطفى فقد أمركم الله بذلك فقال جل من قائل عليماً: (إِنَّ اللَّهَ وَمَلائِكَتَهُ يُصَلُّونَ عَلَى النَّبِيِّ يَا أَيُّهَا الَّذِينَ آمَنُوا صَلُّوا عَلَيْهِ وَسَلِّمُوا تَسْلِيماً)[الأحزاب:٥٦].",
  "htmlContent": "<div>\n                                                            <div style=\"margin-bottom: 2rem\">\n                        <h5>عناصر الخطبة</h5>\n                        <span>1/عظم آية الشيب 2/الشيب بداية مرحلة الضعف وقرب الأجل 3/فضل الشيب 4/حقوق أهل المشيب 5/ عظة للشباب وأهل الشيب</span>\n                    </div>\n                                                                                                                                                                                                                        </div>\n                                <div class=\"border-gray-bg-div excerpt\">\n                    <h2 class=\"red-color\"><i class=\"fas fa-quote-right\"></i> اقتباس</h2>\n                    <p class=\"text-justify\">فبينما الإنسانُ يعيشُ أيامَ شبابِهِ في أوجِ قوّتهِ، وعنفوانِ فتوتِه، ويؤمَّل طولَ بقائهِ في الدنيا، وقد ملأَ أيّامها نشاطًا وحيويةً، وتعلّق قلبُه بطول العمر؛ إذ ينقلب كل ذلك؛ فورقات شجرةِ عمرهِ تتهافت، وسنواتُها تتعاقبْ، وأحوالُه تتغيَّر، ويذبلُ عزُّه، ويبدأ ذُله، فيبيضُّ شعرُه، ويتجعَّدُ وجهُه، ويحدودبُ ظهرُه، وتهنُ حواسُّه، وتضعفُ ذاكرتُه، وتتغيَّر عافيتُه؛ فالشيبُ هو ناقوسُ...</p>\n                </div>\n                                <div class=\"div-30\"></div>\n                <div id=\"body\" data-post=\"303004\" class=\"subject-content\" style=\"text-align: right;\">\n                    <p>الخطبة الأولى:</p>\n<p>&nbsp;</p>\n<p>إنّ الحمدَ للهِ نحمدهُ ونستعينهُ ونستغفرُه، ونعوذ بالله من شرور أنفسنا وسيئات أعمالنا، من يهده الله فلا مضل له، ومن يضلل فلا هادي له، وأشهدُ أن لا إله إلا اللهُ وحده لا شريك له، وأشهدُ أنّ محمدًا عبدُهُ ورسولُهُ صلى الله عليه وعلى آله وصحبه ومن تبعهم بإحسان إلى يوم الدين وسلّم تسليمًا كثيرًا.</p>\n<p>&nbsp;</p>\n<p>أمّا بعد: فاتقوا الله -عباد الله-، واعلموا أن التقوى طريقُ النجاة والفوز برضا الرحمن (<span style=\"color: #ff0000;\">يَا أَيُّهَا الَّذِينَ آمَنُوا اتَّقُوا اللَّهَ وَقُولُوا قَوْلاً سَدِيداً * يُصْلِحْ لَكُمْ أَعْمَالَكُمْ وَيَغْفِرْ لَكُمْ ذُنُوبَكُمْ وَمَن يُطِعِ اللهَ وَرَسُولَهُ فَقَدْ فَازَ فَوْزَاً عَظِيماً</span>) [الأحزاب:70-71].</p>\n<p>&nbsp;</p>\n<p>عباد الله: لقد جعل اللهُ -تعالى- في خلقهِ آياتٍ عظيمةً، وبراهينَ عديدةً، تَظهرُ فيها قدرةُ وعظمةُ الخالق الجليل، وصدق الله -تعالى-: (<span style=\"color: #ff0000;\">سَنُرِيهِمْ آَيَاتِنَا فِي الْآَفَاقِ وَفِي أَنْفُسِهِمْ حَتَّى يَتَبَيَّنَ لَهُمْ أَنَّهُ الْحَقُّ</span>)[فصلت: 53] وقال تعالى: (<span style=\"color: #ff0000;\">وَكَأَيِّنْ مِنْ آيَةٍ فِي السَّمَوَاتِ وَالأَرْضِ يَمُرُّونَ عَلَيْهَا وَهُمْ عَنْهَا مُعْرِضُونَ</span>)[النحل: 105].</p>\n<p>&nbsp;</p>\n<p>ومن تلك الآياتِ الباهرةِ التي غفل عنها كثيرٌ من الناسِ آيةُ المشيبِ التي تصيبُ الإنسانَ في آخرِ سنواتِ عمرهِ، تلك الآيةُ التي ذكرها اللهُ -تعالى- في كتابهِ العزيزِ كما في قوله -جلّ وعلا- عن زكريا عليه السلام: (<span style=\"color: #ff0000;\">قَالَ رَبِّ إِنِّي وَهَنَ الْعَظْمُ مِنِّي وَاشْتَعَلَ الرَّأْسُ شَيْباً وَلَمْ أَكُنْ بِدُعَائِكَ رَبِّ شَقِيّاً</span>)[مريم:4].</p>\n<p>&nbsp;</p>\n<p>تلك الآيةُ العظيمةُ التي يُظهرِها اللهُ -تعالى- في كثيرٍ من خلقهِ ويغفلونَ عما وراءها من العبرِ والعظاتِ، والإنسانُ في هذهِ الدنيا يعيشُ بين ضَعْفَين، ضَعْفٌ في مبدأِ طفولتِهِ، ثم ضعفٍ وَوَهنٍ عند نهايتِهِ وشيخوختِه، وهذا الضعفُ والنقصُ المحاطُ به الإنسانُ، هو من جملةِ آياتِ اللهِ -تعالى- التي وضعها في خلقِهِ للاعتبارِ والتذكرِ؛ قال جلّ وعلا: (<span style=\"color: #ff0000;\">اللَّهُ الَّذِي خَلَقَكُمْ مِنْ ضَعْفٍ ثُمَّ جَعَلَ مِنْ بَعْدِ ضَعْفٍ قُوَّةً ثُمَّ جَعَلَ مِنْ بَعْدِ قُوَّةٍ ضَعْفًا وَشَيْبَةً يَخْلُقُ مَا يَشَاءُ وَهُوَ الْعَلِيمُ الْقَدِيرُ</span>)[الروم:54]؛ فتعالوا بنا نقفُ مع ضعفٍ يسبقُنا، أو قد حلَّ ببعضِنا، مع الشيبِ والمشيبِ، وهمّهِ وهمومِه، وحلوهِ ومُرِّه، وعِبرِه وعَبَراتِهِ.</p>\n<p>&nbsp;</p>\n<p>أيّها المؤمنون والمؤمنات: حياةُ الكهولةِ والمشيبِ محطةٌ لا بدّ منها لمنْ أمدَّ اللهُ في عمرِهِ، وأنسأَ لهُ في أثرِهِ، وهي حياةٌ تبعثُ على الإشفاقِ، والرأفةِ، والرحمةِ.</p>\n<p>&nbsp;</p>\n<p>مرحلةٌ تحملُ في طيّاتها تغيرًا كثيرًا في الخلقةِ والطبعِ والطبائعِ.</p>\n<p>&nbsp;</p>\n<p>تأمّلوا معي -عباد الله- عظيمَ قدرةِ اللهِ وصُنعهِ في عبدِه؛ فبينما الإنسانُ يعيشُ أيامَ شبابِهِ في أوجِ قوّتهِ، وعنفوانِ فتوتِه، ويؤمَّل طولَ بقائهِ في الدنيا، وقد ملأَ أيّامها نشاطًا وحيويةً، وتعلّق قلبُه بطول العمر؛ إذ ينقلب كل ذلك؛ فورقات شجرةِ عمرهِ تتهافت، وسنواتُها تتعاقبْ، وأحوالُه تتغيَّر، ويذبلُ عزُّه، ويبدأ ذُله، فيبيضُّ شعرُه، ويتجعَّدُ وجهُه، ويحدودبُ ظهرُه، وتهنُ حواسُّه، وتضعفُ ذاكرتُه، وتتغيَّر عافيتُه؛ فالشيبُ هو ناقوسُ الضعفِ، ونذيرُ الفناءِ، والعجزِ بعد القوّةِ، والعلةُ التي لا تبرأُ، والدليلُ على قربِ الرحيلِ.</p>\n<p>&nbsp;</p>\n<p>وهو آيةٌ عظيمةٌ على قربِ نهايةِ عمر الإنسانِ، ومنتهى حياتِهِ، وصدقَ اللهُ -تعالى-: (<span style=\"color: #ff0000;\">وَمَنْ نُعَمِّرْهُ نُنَكِّسْهُ فِي الْخَلْقِ أَفَلا يَعْقِلُونَ</span>)[يس: 68].</p>\n<p>&nbsp;</p>\n<p>وإذا شابَ المرءُ فقدْ أعذَرَه ربُّه بتعميرِه، وإمدادِهِ في فسحةِ حياتِهِ، وقد اشتدَّ عتابُ اللهِ على أقوامٍ عاشوا طويلاً، وامتدتْ حياتُهم، لكنّهم لم ينتفعوا بأعمارهمْ؛ قال تعالى: (<span style=\"color: #ff0000;\">أَوَلَمْ نُعَمِّرْكُمْ مَا يَتَذَكَّرُ فِيهِ مَنْ تَذَكَّرَ وَجَاءَكُمُ النَّذِيرُ فَذُوقُوا فَمَا لِلظَّالِمِينَ مِنْ نَصِيرٍ</span>)[فاطر: 37]، وقد فسَّره بعضُ العلماءِ بأنّه الشيبُ.</p>\n<p>&nbsp;</p>\n<p>فأهلُ القلوبِ الحيَّةِ يعتبرون هذا الشيبَ نَذارةً من ربّهم؛ ليستعدوا بالعملِ، قبلَ حلولِ الأجلِ، فليسَ بعد هذا المشيبِ بضعفهِ ووهنهِ إلّا رذائلُ الأعمارِ، والانتقالُ من هذهِ الدّارِ.</p>\n<p>&nbsp;</p>\n<p>عبادَ اللهِ: إنّ هذا المشيبَ، وإنْ جاءَ بالضعفِ والعجزِ والحزنِ، إلا أنّه يحملُ بين طياتِهِ الأجرَ العظيمَ، والثوابَ الجزيلَ، لمن تحلّى بالصبرِ، وآمن بالقضاءِ والقدرِ؛ فهو في حياتِه كلّها في خيرٍ، وعلى خيرٍ، يقولُ -صلى الله عليه وسلم-: \"<span style=\"color: #0000ff;\">عجبًا لأمرِ المؤمنِ، إنّ أمرَهُ كلَّهُ خير، وليسَ ذاك لأحدٍ إلا للمؤمنِ، إن أصابتْهُ سرّاءُ شَكَرَ، فكانَ خيْرًا لهُ، وإنْ أصابتْهُ ضرّاءَ صبرَ، فكانَ خيْرًا لهُ</span>\"(رواه مسلم).</p>\n<p>&nbsp;</p>\n<p>فأهلُ الشيبِ في الإسلامِ لهمْ من المكانةِ والفضلِ ما ليسَ لمنْ دونهمْ، فإنّ رسولَ اللهِ -صلى اللهُ عليه وسلّم- قَرَنَ إِجْلالَ اللهِ بإجلالِهِمْ ؛ قالَ -صلى الله عليه وسلم-: \"<span style=\"color: #0000ff;\">إنّ مِنْ إجلالِ اللهِ -تعالى- إكرامَ ذي الشيبةِ المسلمِ</span>\"(رواه البخاري في الأدب المفرد، وأبو داود، وحسنه الألباني في سنن أبي داود).</p>\n<p>&nbsp;</p>\n<p>وكافأهم أيضًا بحطِّ السيّئاتِ، وزيادةِ الحسناتِ، ورفعةِ الدرجاتِ ؛ قال -صلى الله عليه وسلم-: \"<span style=\"color: #0000ff;\">لَا تَنْتِفُوا الشّيْبَ فَإِنّهُ مَا مِنْ مُسْلِمٍ يَشِيبُ شَيْبَةً فِي الإِسْلَامِ إلّا كتبَ اللهُ لهُ بِهَا حَسَنَةً وَحَطّ عنهُ بِهَا خَطِيئةً</span>\"(رواه أبو داود والترمذي، وصححه الألباني في صحيح الترغيب والترهيب).</p>\n<p>&nbsp;</p>\n<p>وأبدلهـم -سبحانه وتعالى- بهذا الشيبِ نورًا؛ قال -صلى الله عليه وسلم-: \"<span style=\"color: #0000ff;\">مَنْ شَابَ شَيْبَةً فِي الِإسلامِ، كانتْ لهُ نورًا يومَ القِيَامةِ</span>\"(رواه ابن حبان بسند حسن).</p>\n<p>&nbsp;</p>\n<p>وسُئل النبي -صلى الله عليه وسلم-: أيُّ النَّاسِ خيرٌ؟ قال: \"<span style=\"color: #0000ff;\">مَنْ طَالَ عُمْرُهُ وَحَسُنَ عَمَلُهُ</span>\"، قال: فأيُّ النَّاسِ شرٌّ؟ قال: \"<span style=\"color: #0000ff;\">منْ طالَ عُمْرُهُ وَسَاءَ عَمَلُهُ</span>\"(رواه الترمذي، وصححه الألباني في سنن الترمذي)؛ فطوبى لمنْ شابَ رأسُهُ، وابْيّضَ شعرُهُ، وهو مستقيمٌ على طاعة رَبّهِ. قال الحسنُ البصريُّ: \"<span style=\"color: #008000;\">أفضلُ الناسِ ثوابًا يومَ القيامةِ المؤمنُ المعمَّرُ</span>\".</p>\n<p>&nbsp;</p>\n<p>فإذا استقامتْ أحوالُ أهلِ المشيبِ وصلَحتْ أعمالُهم وحسُنت سيرتُهم؛ كانوا أقربَ النّاسِ إلى ربّهم -عزّ وجلّ-، وأهلاً للرحمةِ وإجابةِ الدعاءِ.</p>\n<p>&nbsp;</p>\n<p>قال اللهُ -تعالى-: (<span style=\"color: #ff0000;\">اللَّهُ الَّذِي خَلَقَكُمْ مِنْ ضَعْفٍ ثُمَّ جَعَلَ مِنْ بَعْدِ ضَعْفٍ قُوَّةً ثُمَّ جَعَلَ مِنْ بَعْدِ قُوَّةٍ ضَعْفاً وَشَيْبَةً يَخْلُقُ مَا يَشَاءُ وَهُوَ الْعَلِيمُ الْقَدِيرُ</span>)[الروم:54].</p>\n<p>&nbsp;</p>\n<p>باركَ اللهُ لي ولكُمْ في القرآنِ العظيمِ ونفعني وإياكمْ بما فيهِ من الآياتِ والذِّكْرِ الحكيمِ أقولُ قولي هذا وأستغفرُ اللهَ لي ولكمْ منْ كلِّ ذنْبٍ فاستغفروهُ؛ إنّهُ هو الغفورُ الرحيم.</p>\n<p>&nbsp;</p>\n<p>&nbsp;</p>\n<p>الخطبة الثانية:</p>\n<p>&nbsp;</p>\n<p>الحمدُ للهِ على فضلِهِ وإحسانِهِ، والشكرُ لهُ على توفيقِهِ وامتنانِهِ، وأشهدُ أنْ لا إلهَ إلّا اللهُ وحدهُ لا شريكَ لهُ، وأشهدُ أنّ محمدًا عبدُ اللهِ ورسولُهُ صلى اللهُ عليهِ وعلى آلهِ وصحبهِ ومنْ سارَ على نهجِهِ إلى يومِ الدّينِ.</p>\n<p>&nbsp;</p>\n<p>أمَا بعدُ:</p>\n<p>&nbsp;</p>\n<p>فيا أيها المؤمنون والمؤمنات: اتقوا الله –تعالى-، واعلموا أن تقواه سبيل إلى نيل رضاه وجنته.</p>\n<p>&nbsp;</p>\n<p>عباد الله: إنّ الشيبَ -وإنْ أَنِفَهُ بعضُ النّاس- يُعتبر عُنوانَ وَقارٍ وتَاجَ هيبةٍ ورمزَ إجلالٍ ورزانةٍ؛ فحرِيٌّ بمنْ ابيضّ عارضاهُ أنْ يحفظَ وقارَهُ وهيبتَه، وأن يبيّضَ صحيفتَهُ، وأنْ يكثرَ منْ حسناتِهِ.</p>\n<p>&nbsp;</p>\n<p>فعلينا أن نُوقِّر أهل المشيبِ ونَحترمُهُمْ، وأنْ نُصغِي لحديثِهِم، وأنْ نَقضي حَوائجهمْ، وأن نُقدّمهم في المجالسِ؛ لما روي عنْ أنس بن مالك -رضي الله عنه- قال: جاء شيخ غريب يريد النبيَّ -صلى الله عليه وسلم- فأبطأَ الناسُ أنْ يُوسِّعوا له، فقال النبي-صلى الله عليه وسلم-: \"<span style=\"color: #0000ff;\">ليسَ منّا مَنْ لمْ يرحمْ صغيرَنا، ويوقّر كبيرَنا</span>\"(رواه الترمذي، وصححه الألباني في جامع الترمذي).</p>\n<p>&nbsp;</p>\n<p>ولما روي أيضًا عن عبد الله بن عمر -رضي الله عنهما- أنّ رسول الله -صلى الله عليه وسلم- قال: \"إ<span style=\"color: #0000ff;\">نَّ مِنَ الشّجَرِ شجرةً لا يسقطُ ورقُهَا وهو مثلُ المؤمنِ حدّثُوني ما هي</span>؟\"، قال عبدُ الله: فوقعَ النّاسُ في شجرِ البوادي ووقعَ في نفسي أنّهَا النّخْلةُ، فقال النبي -صلى الله عليه وسلم-: \"<span style=\"color: #0000ff;\">هي النخلةُ</span>\"، فاستحييت أنْ أقول. قال عبد الله: فحدّثت عمرَ بالذي وقعَ في نفسي، فقال: لأنْ تكونَ قلتَهَا أحبُّ إليَّ منْ أنْ يكونَ لي كذا وكذا\"(رواه الترمذي، وصححه الألباني في جامع الترمذي).</p>\n<p>&nbsp;</p>\n<p>وإنّي في مقامي هذا أخاطبُ شبابنَا ممنْ لم يروا المشيب، وأقول لهم: اعتبروا بغيرِكم، واتّعِظُوا بما ترونهُ أمامَ أعينِكُمْ، واعلموا أنّ زمنَ الصِّبا والفُتُوَّةِ ظِلٌّ زائل وبستانٌ ذابل، وتذكّروا أنّ زمنَ المشيبِ قريبٌ، وأنّ العمرَ يمضي والسنوَن تنقضي؛ فاملؤوا رصيدكم بالأعمالِ الصالحةِ، واستعينوا بقوّتكمْ على الإكثارِ من الحسناتِ، ولا تخدعنَّكم الدنيا بزخرفِها.</p>\n<p>&nbsp;</p>\n<p>وتذكَّرْ -يا من علاكَ الشيبُ- أن الفُسحةَ في العمرِ نعمةٌ كبيرةٌ يمنُّ الله بها على عبادهِ؛ فاستثمرْ هذه النّعمةَ فيما يُرضي ربَّكَ ويُعلِي منزلتَك، واستدرِك ما فاتَ بالاستعدادِ لما هو آتٍ. لتكنْ شعراتُ شيبكَ تؤزُّكَ للإِنابةِ إلى ربّك أزًّا، وتحرّك مشاعرَ النّدم في نفسِك على تقصيرك، وتضييعِ عمرِك فيما لا ينفعُ؛ فليس فيما بقي من العمر أطولُ مما فاتَ؛ فبادرْ بالتوبةِ والعمل بقيّة أيامك قبل أن تبادرك المنون، واجعل مسك ختام العمر طاعة وتقوى، صلاة وصيامًا، وصدقة واستغفارًا، سلِّ الله حُسن الخاتمة، واعلم أن من عاش على شيء مات عليه، وأن الأعمال بالخواتيم.</p>\n<p>&nbsp;</p>\n<p>أسأل الله -جل وعلا- أن يبارك لنا في شيوخنا وكبارنا، وأن يثبِّتنا وإياهم على الإيمان، وأن يزيدهم إحسانًا وتقى، وأن يُلبسهم لباسَ الصحة والعافية.</p>\n<p>&nbsp;</p>\n<p>وأسأله جل وعلا أن يجعل خير أعمارنا أواخرها، وخير أعمالنا خواتمهـا، وخير أيامنا يوم نلقاه؛ إنه سميع قريب مجيب.</p>\n<p>&nbsp;</p>\n<p>هذا وصلوا وسلموا على الحبيب المصطفى فقد أمركم الله بذلك فقال جل من قائل عليماً: (<span style=\"color: #ff0000;\">إِنَّ اللَّهَ وَمَلائِكَتَهُ يُصَلُّونَ عَلَى النَّبِيِّ يَا أَيُّهَا الَّذِينَ آمَنُوا صَلُّوا عَلَيْهِ وَسَلِّمُوا تَسْلِيماً</span>)[الأحزاب:٥٦].</p>\n\n                </div>",
  "attachments": [
    {
      "name": "آية_الشيب.doc",
      "path": "/database/files/آية_الشيب.doc",
      "link": "https://khutabaa.com/article/%D8%A2%D9%8A%D8%A9-%D8%A7%D9%84%D8%B4%D9%8A%D8%A8/download-file/303005"
    }
  ],
  "mainCategories": [
    {
      "name": "أحوال القلوب",
      "link": "https://khutabaa.com/ar/posts_category/3925"
    },
    {
      "name": "أخلاق وحقوق",
      "link": "https://khutabaa.com/ar/posts_category/3933"
    }
  ],
  "subCategories": [],
  "url": "https://khutabaa.com/ar/article/آية-الشيب"
}
