{
  "id": 3381,
  "title": "أتحب أولادك؟!",
  "slug": "أتحب-أولادك-",
  "author": {
    "name_prefix": "الشيخ",
    "first_name": "راشد بن عبدالرحمن",
    "last_name": "البداح"
  },
  "rawContent": "عناصر الخطبة\n                        1/صور من محبة النبي للأطفال 2/محبة النبي لابنته فاطمة 3/الحث على إظهار مشاعر الحب للأولاد 4/الصبر على الأولاد والدعاء لهم\n                    \n                                                                                                \n                                \n                     اقتباس\n                    اقترِبُوا من قلوبِ أولادِكم، لا سيَما البناتِ، وربَما تقولانِ: \"ابْنَتُنا خَجولةٌ!\"، فيُقالُ: كلَّا، ولكنها حُرِمَتْ من عاطفةٍ أنثويةٍ، فلا حِوَارَ ولا ابتسامةَ ولا ممازحةَ، فإنْ لم تُشْبِعها أُسرتُها من هذهِ العاطفةِ اسْتَغِلَّها متسوِرُو أسوارِنا، من لصوصِ وسائلِ التواصلِ...\n                \n                                \n                \n                    الخُطْبَةُ الأُولَى:\n \nالحَمْدُ للهِ الذيْ لا خَيْرَ إلا مِنهُ، ولا فَضْلَ إلا مِن لَدُنْهُ، وأَشْهَدُ أنْ لا إلهَ إلا اللهُ وَحْدَهُ لا شَرِيْكَ له الحَقُ المُبِيْنُ، وأَشْهَدُ أنَّ مُحَمَّدًا عَبْدُهُ ورَسُوْلُهُ اَلأمِينُ، صَلَّى اللهُ وسلَّمَ علَيهِ.\n \nأمَّا بَعْدُ: فَاتَّقُوا اللهَ (وَاعْلَمُوا أَنَّكُمْ مُلَاقُوهُ)[البقرة: 223].\n \nفيا لَجَمَالِ تلكَ العاطفةِ الرائقةِ الرائعةِ التي يتذوقُها الوالدُ بنشوةٍ وهو ينادِي ولدَه: \"يا ولدِي يا بنتِي!\"، أو يستمعُ لندائِهم: \"يا أبي!\"؛ إنها عاطفةُ الأبوةِ والأمومةِ، فهل تُراكَ تُحبُ وتُحببُ أولادَك إليكَ؟!.\n \nوقد كانَ نبيُكم -صَلَّى اللهُ عَلَيْهِ وَسَلَّمَ- يمارسُ الحبَ لأولادِه شعيرةً ظاهرةً معلنةً، وكان يُطعمُهمُ الحبَ، حتى كأنَها وجبةٌ أو ارتواءٌ مشاعريٌ؛ ليُحَقِّقَ لهم الارتواءَ العاطفيَ والإشباعَ النفسيَ.\n \nوخذْ على ذلكَ أمثلةً رقيقةً رقراقةً: في صحيحَيِ البخاريِ ومسلمٍ: يقولُ أَبو هُرَيْرَةَ -رَضِيَ اللَّهُ عَنْهُ-: كُنْتُ مَعَ رَسُولِ اللَّهِ -صَلَّى اللهُ عَلَيْهِ وَسَلَّمَ- فَجَلَسَ بِفِنَاءِ بَيْتِ فَاطِمَةَ، فَقَالَ مستمْلِحًا لسِبطه: أَيْنَ لُكَعُ؟! أَيْنَ لُكَعُ؟! أَيْنَ لُكَعُ؟! ادْعُ الْحَسَنَ بْنَ عَلِيٍّ، فغَسَّلَتْهُ أُمُّه وَأَلْبَسَتْهُ فِي عُنُقِهِ قلادةً تَنْفَحُ طِيبًا، فَجَاءَ يَشْتَدُّ حَتَّى عَانَقَهُ وَقَبَّلَهُ نبيُّك -صَلَّى اللهُ عَلَيْهِ وَسَلَّمَ-، ثم قَالَ يُسمِعُه ويُسمِعُ أمَه والأُمَّةَ كلَها: \"اللَّهُمَّ إِنِّي أُحِبُّهُ فَأَحِبَّهُ، وَأَحِبَّ مَنْ يُحِبُّهُ\"(متفق عليه)، فاللهم إنا نحبُ رسولَكَ محمدًا، وسِبطَ رسولِك الحسنَ.\n \nإنها عظمةُ المشاعرِ المحمديةِ الدالةِ على خلفيةٍ طويلةٍ في بناءِ العلاقةِ العاطفيةِ؛ فكان الترحيبُ ببسطِ اليدينِ، ثم العناقِ، ثم التقبيلِ، ثم سَكَبَ هذا الحبَ مُعلنًا في مسامعهِ دعاءً: \"اللهم إني أحبّهُ\".\n \nواستمعِ الآنَ لهذا الموقفِ الذي يَقطرُ عذوبةً ولطفًا، ويَذوبُ رقةً وعطفًا، فمن جنسِ الذكورِ إلى جنسِ الإناثِ، حيثُ كان تعامُلُه -صَلَّى اللهُ عَلَيْهِ وَسَلَّمَ- مع البناتِ على أرقَى وأرقِّ المستوياتِ، فكانَ إذا زارتْه ابنتُه فاطمةُ قامَ إليها يَتلقَاها ويرحِبُ بها قائلاً: \"مَرْحَبًا بِابْنَتِي\"(متفق عليه)، ثم يأخذُ بيدِها ويُقبِلُها، ويُجْلِسُها في مكانهِ الذي كانَ جالسًا فيه؛ مبالغةً في الحفاوةِ والمحبةِ والإكرامِ، وكانَ يُعلنُ حُبَها والدفاعَ عنها قائلاً: \"فَاطِمَةُ بَضْعَةٌ مِنِّي، فَمَنْ أَغْضَبَهَا أَغْضَبَنِي\"(متفق عليه).\n \nفلما مرِضَ مَرَضَه الذي توفيَ فيه أرسلَ إلى البَضعةِ النبويةِ يَدْعُوها، فأقبلَتْ تمشِي، لا تُخطيءُ مِشيتُها مِشيةَ أبِيها -صَلَّى اللهُ عليهِ وسلَّمَ-، ولكنهُ هذه المرّةُ لم يَقُمْ لها كما كانَ يقومُ؛ لأن العافيةَ قد انهزمتْ في بدنِهِ الشريفِ، فقد أنهكتْه الحُمى، وإذ بفاطمةَ تَنكَبُّ عليه تُقبّلُه، وقد كان هوَ الذي يبادِرُ بتقبيلِها.\n \nبقيَ أن نعرفَ أعجَبَ ما في هذا الموقفِ، وهوَ أن هذا التدفقَ العاطفيَ النبويَ والحبَ المحمديَ الأبويَ كانَ لفاطمةَ وهيَ في الخامسةِ والعشرينَ من عُمُرِها زوجةً وأمًا لخمسةِ أولادٍ.\n \nفلنسألْ أنفسَنا: هل نحنُ واضحونَ في تعبيرِنا عن مشاعرِ الحبِ لأولادِنا الكبارِ؟ أم نظنُ أنهم استغنَوا عن تصريحِنا لهم بالحبِ لما كبُرُوا؟ ألا فلنوقِن أن الأولادَ يَكبرونَ ويَكبُرُ حُبُهم معهم، وليسوا لُعَبًا يُلهَى بهم صغارًا، ويُهْمَلونَ كبارًا، فسَلْ نفسَك: متى كانتْ آخرُ رسالةٍ أرسلتُها لابِني وبنتِي أُخبرُهُما أني أُحبُهُما؟!.\n \nوفي مشهدٍ نبويٍ ثالثٍ يُعجبُكَ وتَعجبُ منه: فاجأَ -صَلَّى اللهُ عَلَيْهِ وَسَلَّمَ- أصحابَه حين خرجَ إلى صلاةِ العصرِ وعلى عاتقِهِ ابنتُه أمامةُ بنتُ بنتهِ زينبَ، فصلَى بهم وهيَ على عاتقهِ، إذا ركعَ وضعَها، وإذا قامَ رفعَها.(رواه البخاري).\n \nوإن الأنوثةَ في هذا المشهدِ أنوثةٌ مضاعفةٌ، فهيَ بنتُ بنتِه؛ ليُقدمَ درساً عملياً في الحفاوةِ بالحفيداتِ، ولِيقضيَ على بقايا الجاهليةِ في النفوسِ التي كانت ترَى في الأنثَى سَوءةً يُخفِيها أبُوها، بل و(يَتَوَارَى مِنَ الْقَوْمِ مِنْ سُوءِ مَا بُشِّرَ بِهِ)[النحل: 59]، فما أبعدَ المفارقةَ بين من يتوارَى من القومِ لأنه بُشِّرَ بالأنثَى، ومن يَخرجُ إلى الناسِ وعلى عاتقهِ البنتُ الأُنثَى.\n \n \nالخطبة الثانية:\n \nالحمدُ للهِ خيرِ محمودٍ، والصلاةُ والسلامُ على خيرِ حامدٍ، أما بعدُ:\n \nأيُها الآباءُ والأمهاتُ: اقترِبُوا من قلوبِ أولادِكم، لا سيَما البناتِ، وربَما تقولانِ: \"ابْنَتُنا خَجولةٌ!\"، فيُقالُ: كلَّا، ولكنها حُرِمَتْ من عاطفةٍ أنثويةٍ، فلا حِوَارَ ولا ابتسامةَ ولا ممازحةَ، فإنْ لم تُشْبِعها أُسرتُها من هذهِ العاطفةِ اسْتَغِلَّها متسوِرُو أسوارِنا، من لصوصِ وسائلِ التواصلِ.\n \nفافْتَحُوا قُلُوبَكم لهنَّ، وحاوِرُوهُنَّ، وعِيشُوا مشاكلَهُنَّ، وأَسمِعوهُنَّ دومًا كلمةَ: أحبكِ، وكونُوا الحِضْنَ الدافئَ، والحِصْنَ الآمنَ.\n \nأَيُّها الوالدانِ: لا يَشُكُّ في محبَّتِكم لأولادِكم، وقد يُرهقونَكم في مراهقتِهم، فيُقِضُّونَ مضاجعَكم بسهرِهِم، وبإهمالهِم لصلاتِهم ودراستِهم.\n \nفيُقال: تمهَلُوا واقتربُوا، ثم أينَ أنتم مِنْ كثرةِ الدعاءِ لهم بالصلاحِ؟ كم مرةً دعوتَ لأولادِك في وجوهِهم، وفي غَيبتِهم؟ فبعضُنا يَغْفَلُ كثيرًا عنِ الدعاءِ، والدعاءُ يختصرُ لكَ الطريقَ في تربيتِهم، وحفظِهم، وصلاحِهم.\n \nفاللهم ربَنا هبْ لنا من أزواجِنا وذرياتِنا قرةَ أعينٍ واجعلنا للمتقينَ إمامًا، اللهم اجزِ والدَينا كما ربّونا صغارًا خيرَ الجزاءِ، اللهم احفظْ أولادَنا، وارزقهم مزيدَ التبصرِ بكيدِ متبعِي الشهواتِ، الذين يريدونَ أن نميلَ ميلاً عظيمًا، اللَّهُمَّ صُبَّ عَليْنا الخَيْر صَبَّا صَبَّا، ولا تَجْعَل عَيْشَنَا كَدَّا، اللهم بارَكْ في عُمُرِ وليِّ أمرِنا وولي عهده، وزدهم عزًا وبذلاً في نصرةِ الإسلامِ وخدمةِ المسلمينِ، اللهم واكفِنا وبلادَنا كيدَ الفجارِ، وانصرْ مجاهدِينا ومرابطِينا، اللهم وانصرْ المستضعفينَ من المسلمينَ في بقاعِ الأرضِ.\n \nاللهم صلِ وسلِم على محمدٍ.",
  "htmlContent": "<div>\n                                                                                                                                                                                    <div style=\"margin-bottom: 2rem\">\n                        <h5>عناصر الخطبة</h5>\n                        <span>1/صور من محبة النبي للأطفال 2/محبة النبي لابنته فاطمة 3/الحث على إظهار مشاعر الحب للأولاد 4/الصبر على الأولاد والدعاء لهم</span>\n                    </div>\n                                                                                                </div>\n                                <div class=\"border-gray-bg-div excerpt\">\n                    <h2 class=\"red-color\"><i class=\"fas fa-quote-right\"></i> اقتباس</h2>\n                    <p class=\"text-justify\">اقترِبُوا من قلوبِ أولادِكم، لا سيَما البناتِ، وربَما تقولانِ: \"ابْنَتُنا خَجولةٌ!\"، فيُقالُ: كلَّا، ولكنها حُرِمَتْ من عاطفةٍ أنثويةٍ، فلا حِوَارَ ولا ابتسامةَ ولا ممازحةَ، فإنْ لم تُشْبِعها أُسرتُها من هذهِ العاطفةِ اسْتَغِلَّها متسوِرُو أسوارِنا، من لصوصِ وسائلِ التواصلِ...</p>\n                </div>\n                                <div class=\"div-30\"></div>\n                <div id=\"body\" data-post=\"380162\" class=\"subject-content\" style=\"text-align: right;\">\n                    <p>الخُطْبَةُ الأُولَى:</p>\n<p>&nbsp;</p>\n<p>الحَمْدُ للهِ الذيْ لا خَيْرَ إلا مِنهُ، ولا فَضْلَ إلا مِن لَدُنْهُ، وأَشْهَدُ أنْ لا إلهَ إلا اللهُ وَحْدَهُ لا شَرِيْكَ له الحَقُ المُبِيْنُ، وأَشْهَدُ أنَّ مُحَمَّدًا عَبْدُهُ ورَسُوْلُهُ اَلأمِينُ، صَلَّى اللهُ وسلَّمَ علَيهِ.</p>\n<p>&nbsp;</p>\n<p>أمَّا بَعْدُ: فَاتَّقُوا اللهَ (<span style=\"color:#ff0000;\">وَاعْلَمُوا أَنَّكُمْ مُلَاقُوهُ</span>)[البقرة: 223].</p>\n<p>&nbsp;</p>\n<p>فيا لَجَمَالِ تلكَ العاطفةِ الرائقةِ الرائعةِ التي يتذوقُها الوالدُ بنشوةٍ وهو ينادِي ولدَه: \"<span style=\"color:#008000;\">يا ولدِي يا بنتِي</span>!\"، أو يستمعُ لندائِهم: \"<span style=\"color:#008000;\">يا أبي</span>!\"؛ إنها عاطفةُ الأبوةِ والأمومةِ، فهل تُراكَ تُحبُ وتُحببُ أولادَك إليكَ؟!.</p>\n<p>&nbsp;</p>\n<p>وقد كانَ نبيُكم -صَلَّى اللهُ عَلَيْهِ وَسَلَّمَ- يمارسُ الحبَ لأولادِه شعيرةً ظاهرةً معلنةً، وكان يُطعمُهمُ الحبَ، حتى كأنَها وجبةٌ أو ارتواءٌ مشاعريٌ؛ ليُحَقِّقَ لهم الارتواءَ العاطفيَ والإشباعَ النفسيَ.</p>\n<p>&nbsp;</p>\n<p>وخذْ على ذلكَ أمثلةً رقيقةً رقراقةً: في صحيحَيِ البخاريِ ومسلمٍ: يقولُ أَبو هُرَيْرَةَ -رَضِيَ اللَّهُ عَنْهُ-: كُنْتُ مَعَ رَسُولِ اللَّهِ -صَلَّى اللهُ عَلَيْهِ وَسَلَّمَ- فَجَلَسَ بِفِنَاءِ بَيْتِ فَاطِمَةَ، فَقَالَ مستمْلِحًا لسِبطه: أَيْنَ لُكَعُ؟! أَيْنَ لُكَعُ؟! أَيْنَ لُكَعُ؟! ادْعُ الْحَسَنَ بْنَ عَلِيٍّ، فغَسَّلَتْهُ أُمُّه وَأَلْبَسَتْهُ فِي عُنُقِهِ قلادةً تَنْفَحُ طِيبًا، فَجَاءَ يَشْتَدُّ حَتَّى عَانَقَهُ وَقَبَّلَهُ نبيُّك -صَلَّى اللهُ عَلَيْهِ وَسَلَّمَ-، ثم قَالَ يُسمِعُه ويُسمِعُ أمَه والأُمَّةَ كلَها: \"<span style=\"color:#0000ff;\">اللَّهُمَّ إِنِّي أُحِبُّهُ فَأَحِبَّهُ، وَأَحِبَّ مَنْ يُحِبُّهُ</span>\"(متفق عليه)، فاللهم إنا نحبُ رسولَكَ محمدًا، وسِبطَ رسولِك الحسنَ.</p>\n<p>&nbsp;</p>\n<p>إنها عظمةُ المشاعرِ المحمديةِ الدالةِ على خلفيةٍ طويلةٍ في بناءِ العلاقةِ العاطفيةِ؛ فكان الترحيبُ ببسطِ اليدينِ، ثم العناقِ، ثم التقبيلِ، ثم سَكَبَ هذا الحبَ مُعلنًا في مسامعهِ دعاءً: \"<span style=\"color:#0000ff;\">اللهم إني أحبّهُ</span>\".</p>\n<p>&nbsp;</p>\n<p>واستمعِ الآنَ لهذا الموقفِ الذي يَقطرُ عذوبةً ولطفًا، ويَذوبُ رقةً وعطفًا، فمن جنسِ الذكورِ إلى جنسِ الإناثِ، حيثُ كان تعامُلُه -صَلَّى اللهُ عَلَيْهِ وَسَلَّمَ- مع البناتِ على أرقَى وأرقِّ المستوياتِ، فكانَ إذا زارتْه ابنتُه فاطمةُ قامَ إليها يَتلقَاها ويرحِبُ بها قائلاً: \"<span style=\"color:#0000ff;\">مَرْحَبًا بِابْنَتِي</span>\"(متفق عليه)، ثم يأخذُ بيدِها ويُقبِلُها، ويُجْلِسُها في مكانهِ الذي كانَ جالسًا فيه؛ مبالغةً في الحفاوةِ والمحبةِ والإكرامِ، وكانَ يُعلنُ حُبَها والدفاعَ عنها قائلاً: \"<span style=\"color:#0000ff;\">فَاطِمَةُ بَضْعَةٌ مِنِّي، فَمَنْ أَغْضَبَهَا أَغْضَبَنِي</span>\"(متفق عليه).</p>\n<p>&nbsp;</p>\n<p>فلما مرِضَ مَرَضَه الذي توفيَ فيه أرسلَ إلى البَضعةِ النبويةِ يَدْعُوها، فأقبلَتْ تمشِي، لا تُخطيءُ مِشيتُها مِشيةَ أبِيها -صَلَّى اللهُ عليهِ وسلَّمَ-، ولكنهُ هذه المرّةُ لم يَقُمْ لها كما كانَ يقومُ؛ لأن العافيةَ قد انهزمتْ في بدنِهِ الشريفِ، فقد أنهكتْه الحُمى، وإذ بفاطمةَ تَنكَبُّ عليه تُقبّلُه، وقد كان هوَ الذي يبادِرُ بتقبيلِها.</p>\n<p>&nbsp;</p>\n<p>بقيَ أن نعرفَ أعجَبَ ما في هذا الموقفِ، وهوَ أن هذا التدفقَ العاطفيَ النبويَ والحبَ المحمديَ الأبويَ كانَ لفاطمةَ وهيَ في الخامسةِ والعشرينَ من عُمُرِها زوجةً وأمًا لخمسةِ أولادٍ.</p>\n<p>&nbsp;</p>\n<p>فلنسألْ أنفسَنا: هل نحنُ واضحونَ في تعبيرِنا عن مشاعرِ الحبِ لأولادِنا الكبارِ؟ أم نظنُ أنهم استغنَوا عن تصريحِنا لهم بالحبِ لما كبُرُوا؟ ألا فلنوقِن أن الأولادَ يَكبرونَ ويَكبُرُ حُبُهم معهم، وليسوا لُعَبًا يُلهَى بهم صغارًا، ويُهْمَلونَ كبارًا، فسَلْ نفسَك: متى كانتْ آخرُ رسالةٍ أرسلتُها لابِني وبنتِي أُخبرُهُما أني أُحبُهُما؟!.</p>\n<p>&nbsp;</p>\n<p>وفي مشهدٍ نبويٍ ثالثٍ يُعجبُكَ وتَعجبُ منه: فاجأَ -صَلَّى اللهُ عَلَيْهِ وَسَلَّمَ- أصحابَه حين خرجَ إلى صلاةِ العصرِ وعلى عاتقِهِ ابنتُه أمامةُ بنتُ بنتهِ زينبَ، فصلَى بهم وهيَ على عاتقهِ، إذا ركعَ وضعَها، وإذا قامَ رفعَها.(رواه البخاري).</p>\n<p>&nbsp;</p>\n<p>وإن الأنوثةَ في هذا المشهدِ أنوثةٌ مضاعفةٌ، فهيَ بنتُ بنتِه؛ ليُقدمَ درساً عملياً في الحفاوةِ بالحفيداتِ، ولِيقضيَ على بقايا الجاهليةِ في النفوسِ التي كانت ترَى في الأنثَى سَوءةً يُخفِيها أبُوها، بل و(<span style=\"color:#ff0000;\">يَتَوَارَى مِنَ الْقَوْمِ مِنْ سُوءِ مَا بُشِّرَ بِهِ</span>)[النحل: 59]، فما أبعدَ المفارقةَ بين من يتوارَى من القومِ لأنه بُشِّرَ بالأنثَى، ومن يَخرجُ إلى الناسِ وعلى عاتقهِ البنتُ الأُنثَى.</p>\n<p>&nbsp;</p>\n<p>&nbsp;</p>\n<p>الخطبة الثانية:</p>\n<p>&nbsp;</p>\n<p>الحمدُ للهِ خيرِ محمودٍ، والصلاةُ والسلامُ على خيرِ حامدٍ، أما بعدُ:</p>\n<p>&nbsp;</p>\n<p>أيُها الآباءُ والأمهاتُ: اقترِبُوا من قلوبِ أولادِكم، لا سيَما البناتِ، وربَما تقولانِ: \"ابْنَتُنا خَجولةٌ!\"، فيُقالُ: كلَّا، ولكنها حُرِمَتْ من عاطفةٍ أنثويةٍ، فلا حِوَارَ ولا ابتسامةَ ولا ممازحةَ، فإنْ لم تُشْبِعها أُسرتُها من هذهِ العاطفةِ اسْتَغِلَّها متسوِرُو أسوارِنا، من لصوصِ وسائلِ التواصلِ.</p>\n<p>&nbsp;</p>\n<p>فافْتَحُوا قُلُوبَكم لهنَّ، وحاوِرُوهُنَّ، وعِيشُوا مشاكلَهُنَّ، وأَسمِعوهُنَّ دومًا كلمةَ: أحبكِ، وكونُوا الحِضْنَ الدافئَ، والحِصْنَ الآمنَ.</p>\n<p>&nbsp;</p>\n<p>أَيُّها الوالدانِ: لا يَشُكُّ في محبَّتِكم لأولادِكم، وقد يُرهقونَكم في مراهقتِهم، فيُقِضُّونَ مضاجعَكم بسهرِهِم، وبإهمالهِم لصلاتِهم ودراستِهم.</p>\n<p>&nbsp;</p>\n<p>فيُقال: تمهَلُوا واقتربُوا، ثم أينَ أنتم مِنْ كثرةِ الدعاءِ لهم بالصلاحِ؟ كم مرةً دعوتَ لأولادِك في وجوهِهم، وفي غَيبتِهم؟ فبعضُنا يَغْفَلُ كثيرًا عنِ الدعاءِ، والدعاءُ يختصرُ لكَ الطريقَ في تربيتِهم، وحفظِهم، وصلاحِهم.</p>\n<p>&nbsp;</p>\n<p>فاللهم ربَنا هبْ لنا من أزواجِنا وذرياتِنا قرةَ أعينٍ واجعلنا للمتقينَ إمامًا، اللهم اجزِ والدَينا كما ربّونا صغارًا خيرَ الجزاءِ، اللهم احفظْ أولادَنا، وارزقهم مزيدَ التبصرِ بكيدِ متبعِي الشهواتِ، الذين يريدونَ أن نميلَ ميلاً عظيمًا، اللَّهُمَّ صُبَّ عَليْنا الخَيْر صَبَّا صَبَّا، ولا تَجْعَل عَيْشَنَا كَدَّا، اللهم بارَكْ في عُمُرِ وليِّ أمرِنا وولي عهده، وزدهم عزًا وبذلاً في نصرةِ الإسلامِ وخدمةِ المسلمينِ، اللهم واكفِنا وبلادَنا كيدَ الفجارِ، وانصرْ مجاهدِينا ومرابطِينا، اللهم وانصرْ المستضعفينَ من المسلمينَ في بقاعِ الأرضِ.</p>\n<p>&nbsp;</p>\n<p>اللهم صلِ وسلِم على محمدٍ.</p>\n<p>&nbsp;</p>\n\n                </div>",
  "attachments": [
    {
      "name": "أتحب_أولادك؟!.pdf",
      "path": "/database/files/أتحب_أولادك؟!.pdf",
      "link": "https://khutabaa.com/article/%D8%A3%D8%AA%D8%AD%D8%A8-%D8%A3%D9%88%D9%84%D8%A7%D8%AF%D9%83-/download-file/380066"
    },
    {
      "name": "أتحب_أولادك؟!.doc",
      "path": "/database/files/أتحب_أولادك؟!.doc",
      "link": "https://khutabaa.com/article/%D8%A3%D8%AA%D8%AD%D8%A8-%D8%A3%D9%88%D9%84%D8%A7%D8%AF%D9%83-/download-file/380067"
    }
  ],
  "mainCategories": [
    {
      "name": "الأسرة والقرابة",
      "link": "https://khutabaa.com/ar/posts_category/3935"
    },
    {
      "name": "السيرة النبوية",
      "link": "https://khutabaa.com/ar/posts_category/3957"
    }
  ],
  "subCategories": [],
  "url": "https://khutabaa.com/ar/article/أتحب-أولادك-"
}
